PySetWacom/AppIndicator.py
PySetWacom/__init__.py
PySetWacom/__main__.py
PySetWacom/button.py
PySetWacom/device.py
PySetWacom/gui.py
PySetWacom/profile.py
PySetWacom/tray_icon.py
PySetWacom/xmodmap.py
PySetWacom-0.1.8.data/data/share/applications/PySetWacom.desktop
PySetWacom-0.1.8.dist-info/LICENSE
PySetWacom-0.1.8.dist-info/METADATA
PySetWacom-0.1.8.dist-info/WHEEL
PySetWacom-0.1.8.dist-info/entry_points.txt
PySetWacom-0.1.8.dist-info/top_level.txt
PySetWacom-0.1.8.dist-info/RECORD
