Metadata-Version: 2.1
Name: PySetWacom
Version: 0.1.8
Summary: A GUI utility for configuring buttons on graphics tablets and styli
Home-page: https://github.com/domdfcoding/PySetWacom
Author: Dominic Davis-Foster
Author-email: dominic@davis-foster.co.uk
License: GNU Lesser General Public License v3 or later (LGPLv3+)
Project-URL: Documentation, https://PySetWacom.readthedocs.io
Project-URL: Issue Tracker, https://github.com/domdfcoding/PySetWacom/issues
Project-URL: Source Code, https://github.com/domdfcoding/PySetWacom
Platform: UNKNOWN
Classifier: Development Status :: 4 - Beta
Classifier: Intended Audience :: Developers
Classifier: Intended Audience :: End Users/Desktop
Classifier: Operating System :: POSIX :: Linux
Classifier: Topic :: Utilities
Classifier: Topic :: Artistic Software
Classifier: Topic :: Multimedia :: Graphics
Classifier: Programming Language :: Python :: 3.6
Classifier: Programming Language :: Python :: Implementation :: CPython
Classifier: Programming Language :: Python :: 3.7
Classifier: Programming Language :: Python :: 3.8
Classifier: Programming Language :: Python
Classifier: Programming Language :: Python :: 3 :: Only
Classifier: License :: OSI Approved :: GNU Lesser General Public License v3 or later (LGPLv3+)
Requires-Python: >=3.6
Requires-Dist: domdf-python-tools (>=0.1.17)
Requires-Dist: appdirs (>=1.4.3)
Requires-Dist: sh (>=1.12.14)
Requires-Dist: Pypubsub (>=4.0.3)
Requires-Dist: pid (>=2.2.5)
Requires-Dist: domdf-wxpython-tools (>=0.2.0)
Requires-Dist: PyGObject
Provides-Extra: all
